eks_spot_blocks/__init__.py
eks_spot_blocks/py.typed
eks_spot_blocks/_jsii/__init__.py
eks_spot_blocks/_jsii/eks-spot-blocks@0.2.373.jsii.tgz
eks_spot_blocks-0.2.373.dist-info/LICENSE
eks_spot_blocks-0.2.373.dist-info/METADATA
eks_spot_blocks-0.2.373.dist-info/WHEEL
eks_spot_blocks-0.2.373.dist-info/top_level.txt
eks_spot_blocks-0.2.373.dist-info/RECORD
